Workbook

Sheet Cover
B5: GitHub Copilot UBB Transition Kit
B6: Banco BTG Pactual S.A. | TPID 5336866 | Enterprise
B8: Dynamic budget engine, scenario forecasting, optimization program (R1-R7) and execution tracking for the Usage-Based Billing transition.
B10: Paula Silva, Software Global Black Belt
B11: paulasilva@microsoft.com
B12: Version 11.0.0 | 2026-06-12 | Confidential, internal account team use
B14: Companion documents (single source of truth set)
B15: Internal analysis HTML | D15: BTG_Pactual_Analise_Budget_v8 (PT-BR, EN, ES)
B16: Client-facing HTML | D16: BTG_Pactual_Analise_Budget_CLIENTE_v8 (PT-BR, EN, ES)
B17: Data backbone | D17: db.json v2.0.0, Brazil UBB collection (tpid 5336866)
B18: This workbook | D18: Engine, forecast, simulator, action plan and KPI tracking in English
B21: Workbook map
B22: Block | C22: Sheets | D22: What it does
B23: INPUT | C23: Client Intake | D23: everything yellow is editable; the entire kit recalculates
B24: ENGINE | C24: Engine | Consumption FY26 | Model Mix | D24: plan math, audited actuals from db.json, premium concentration
B25: BUSINESS CASE | C25: Dashboard | Forecast FY27 | Simulator | ROI Scenarios | D25: KPIs, September curve, what-if levers, A to D scenario ladder
B26: EXECUTION | C26: Action Plan R1-R7 | 90-Day Plan | Monthly Checkpoints | KPI Tracker | D26: actions with owner and status, weekly cadence, traffic lights
B27: GOVERNANCE | C27: Governance | Maturity | Glossary | Sources | D27: budgets and guardrails, maturity score, definitions, audit trail
B30: Paula Silva, Software Global Black Belt | paulasilva@microsoft.com | Microsoft

Sheet How to Use
B2: GUIDE
B4: How to Use This Kit
B5: Five minutes to understand the flow. Conventions follow finance modeling standards.
B7: Step | C7: What | D7: How
B8: 1 | C8: Fill the Client Intake | D8: Yellow cells only. Client, plan, seats, report consumption, ACD band. Everything downstream recalculates automatically.
B9: 2 | C9: Read the Dashboard | D9: KPIs, the three scenarios, the September curve and the model mix. This is the page you present.
B10: 3 | C10: Pressure-test with the Simulator | D10: Move the R1-R7 reduction levers. Combined effect is multiplicative, never additive, so it cannot exceed 100%.
B11: 4 | C11: Commit to the plan | D11: Action Plan R1-R7, 90-Day Plan and Monthly Checkpoints carry owner, due date and status dropdowns.
B12: 5 | C12: Track weekly | D12: KPI Tracker: enter actuals, variance and traffic lights are automatic. Governance holds the budget guardrails.
B15: Color conventions
B16: Yellow fill | C16: editable input, safe to change
B17: Blue font | C17: hardcoded input value
B18: Black font | C18: formula, do not overwrite
B19: Green font | C19: link from another sheet
B22: Paula Silva, Software Global Black Belt | paulasilva@microsoft.com | Microsoft

Sheet Dashboard
B2: EXECUTIVE DASHBOARD
B4: BTG Pactual, UBB Transition at a Glance
B5: Live view: every number recalculates from Client Intake, Engine, Simulator and the execution sheets.
B7: TODAY (PRU) | E7: NO ACTION (SEP+) | H7: WITH PROMO (JUN-AUG) | K7: SEPTEMBER JUMP | N7: MATURE SAVING / YR | Q7: FY27 PROGRAM SAVINGS
B8: =Engine!C23 -> 130948 | E8: =Engine!C24 -> 231704 | H8: =Engine!C25 -> 137503 | K8: =Engine!C26 -> 94201 | N8: =Simulator!C21 -> 846705.55 | Q8: ='Forecast FY27'!F22 -> 494617.16
B9: per month, audited Apr/26 | E9: per month, +77% vs today | H9: per month, +5% vs today | K9: per month, the deadline | N9: R1-R7 at maturity | Q9: maturity curve
B12: CONSUMPTION / INCLUDED | E12: POOL COVERAGE | H12: CLAUDE FAMILY SHARE | K12: TOP 2 MODELS SHARE | N12: ACTIONS DONE | Q12: BLOCKED ITEMS
B13: =Engine!C18 -> 1.8208709 | E13: =Engine!C19 -> 0.54918776 | H13: ='Model Mix'!C36 -> 0.88548702 | K13: ='Model Mix'!C37 -> 0.69259354 | N13: =COUNTIF('Action Plan R1-R7'!I8:I17,"Done")&" / "&COUNTA('Action Plan R1-R7'!B8:B17) -> 0 / 10 | Q13: =COUNTIF('Action Plan R1-R7'!I8:I17,"Blocked")+COUNTIF('90-Day Plan'!G8:G19,"Blocked") -> 0
B14: pool covers | E14: of consumption | H14: of the token bill | K14: concentration | N14: action plan | Q14: needs attention
B49: Paula Silva, Software Global Black Belt | paulasilva@microsoft.com | Microsoft

Sheet Client Intake
B2: INPUT
B4: Client Intake
B5: Yellow cells drive the entire kit. Audited values from the April 2026 GitHub billing report.
B7: Field | C7: Value | D7: Note
B8: Client name | C8: Banco BTG Pactual S.A. | D8: legal entity
B9: TPID | C9: 5336866 | D9: Microsoft Top Parent ID
B10: Plan | C10: Enterprise | D10: defines included credits and seat price
B11: Business seats (CB) | C11: 1693 | D11: from billing report Apr/2026
B12: Enterprise seats (CE) | C12: 2438 | D12: from billing report Apr/2026
B13: Price per credit (USD) | C13: 0.01 | D13: GitHub list price
B14: Monthly token consumption (USD) | C14: 231704 | D14: total token cost, Apr/2026 report; matches db.json model mix sum
B15: Current monthly PRU overage (USD) | C15: 3699 | D15: old model: spend above included PRU, Apr/2026
B16: Promo window (months covered) | C16: 2 | D16: Jun-Aug 2026 promo; months of FY27 covered (Jul, Aug)
B17: Current ACD band (%) | C17: 0.15 | D17: the Azure discount the new deal must beat
B18: Azure subscription available | C18: Yes | D18: required for the Deal Desk path
B19: Consumption growth, 10 months | C19: 2.68 | D19: Jul/25 to Apr/26; see Consumption FY26 for the computed series
B20: Cost centers | C20: 10 | D20: used by Governance budget split
B23: Paula Silva, Software Global Black Belt | paulasilva@microsoft.com | Microsoft

Sheet Engine
B2: ENGINE
B4: Budget Engine
B5: Plan table, pools, overage and the three scenarios. All formulas, zero hardcoded results.
B7: Plan table (GitHub Copilot list)
B8: Plan | C8: Included std (credits/seat) | D8: Included promo (credits/seat) | E8: Price per seat (USD)
B9: Business | C9: 1900 | D9: 3000 | E9: 19
B10: Enterprise | C10: 3900 | D10: 7000 | E10: 39
B12: Derived (do not edit)
B13: License cost (USD/month) | C13: ='Client Intake'!C11*E9+'Client Intake'!C12*E10 -> 127249
B14: Included pool, standard (USD/month) | C14: =('Client Intake'!C11*C9+'Client Intake'!C12*C10)*'Client Intake'!C13 -> 127249
B15: Included pool, promo (USD/month) | C15: =('Client Intake'!C11*D9+'Client Intake'!C12*D10)*'Client Intake'!C13 -> 221450
B16: Overage, standard (USD/month) | C16: =MAX(0,'Client Intake'!C14-C14) -> 104455
B17: Overage, promo (USD/month) | C17: =MAX(0,'Client Intake'!C14-C15) -> 10254
B18: Consumption / included ratio | C18: =IF(C14=0,0,'Client Intake'!C14/C14) -> 1.8208709
B19: Pool coverage of consumption | C19: =IF('Client Intake'!C14=0,0,MIN(1,C14/'Client Intake'!C14)) -> 0.54918776
B21: The three scenarios
B22: Scenario | C22: USD/month | D22: USD/year | E22: Delta vs today (USD/mo) | F22: Delta vs today (%)
B23: Today (PRU model) | C23: =C13+'Client Intake'!C15 -> 130948 | D23: =C23*12 -> 1571376 | E23: =C23-$C$23 -> 0 | F23: =IF($C$23=0,0,(C23-$C$23)/$C$23) -> 0
B24: No action (Sep 2026 onward) | C24: =C13+C16 -> 231704 | D24: =C24*12 -> 2780448 | E24: =C24-$C$23 -> 100756 | F24: =IF($C$23=0,0,(C24-$C$23)/$C$23) -> 0.7694352
B25: With promo (Jun-Aug 2026) | C25: =C13+C17 -> 137503 | D25: =C25*12 -> 1650036 | E25: =C25-$C$23 -> 6555 | F25: =IF($C$23=0,0,(C25-$C$23)/$C$23) -> 0.050058038
B26: September jump (promo expiry) | C26: =C24-C25 -> 94201 | D26: =(C24-C25)*12 -> 1130412
B27: Annual exposure above today, no action | C27: =(C24-C23)*12 -> 1209072
B29: Paula Silva, Software Global Black Belt | paulasilva@microsoft.com | Microsoft

Sheet Consumption FY26
B2: DATA
B4: Consumption FY26, Audited Series
B5: Monthly actuals from db.json v2.0.0 (MSX FY26). Growth columns are formulas.
B7: Month | C7: GHCP seats | D7: GHCP ACR (USD) | E7: PRU (USD) | F7: PRU units | G7: GHE seats | H7: ACR MoM % | I7: ACR index (Jul=100)
B8: 2025-07 | C8: 1536.3 | D8: 26003 | E8: 14 | F8: 420 | G8: 2325 | I8: =D8/$D$8*100 -> 100
B9: 2025-08 | C9: 1743.7 | D9: 29842 | E9: 24 | F9: 753 | G9: 2347 | H9: =IF(D8=0,0,D9/D8-1) -> 0.14763681 | I9: =D9/$D$8*100 -> 114.76368
B10: 2025-09 | C10: 1895.9 | D10: 32127 | E10: 66 | F10: 2038 | G10: 2361 | H10: =IF(D9=0,0,D10/D9-1) -> 0.076569935 | I10: =D10/$D$8*100 -> 123.55113
B11: 2025-10 | C11: 2114.5 | D11: 36050 | E11: 70 | F11: 2182 | G11: 2387 | H11: =IF(D10=0,0,D11/D10-1) -> 0.12210913 | I11: =D11/$D$8*100 -> 138.63785
B12: 2025-11 | C12: 2323.5 | D12: 40501 | E12: 38 | F12: 1187 | G12: 2393 | H12: =IF(D11=0,0,D12/D11-1) -> 0.12346741 | I12: =D12/$D$8*100 -> 155.75511
B13: 2025-12 | C13: 2424.5 | D13: 43028 | E13: 79 | F13: 2458 | G13: 2404 | H13: =IF(D12=0,0,D13/D12-1) -> 0.062393521 | I13: =D13/$D$8*100 -> 165.47321
B14: 2026-01 | C14: 2620.1 | D14: 47366 | E14: 288 | F14: 8969 | G14: 2412 | H14: =IF(D13=0,0,D14/D13-1) -> 0.10081807 | I14: =D14/$D$8*100 -> 182.15591
B15: 2026-02 | C15: 2809.4 | D15: 52283 | E15: 694 | F15: 21583 | G15: 2420 | H15: =IF(D14=0,0,D15/D14-1) -> 0.10380864 | I15: =D15/$D$8*100 -> 201.06526
B16: 2026-03 | C16: 3776.1 | D16: 80071 | E16: 1462 | F16: 45470 | G16: 3074 | H16: =IF(D15=0,0,D16/D15-1) -> 0.53149207 | I16: =D16/$D$8*100 -> 307.92985
B17: 2026-04 | C17: 3808.9 | D17: 95550 | E17: 2876 | F17: 89450 | G17: 3078 | H17: =IF(D16=0,0,D17/D16-1) -> 0.19331593 | I17: =D17/$D$8*100 -> 367.4576
B18: 2026-05 | C18: 4076.5 | D18: 108722 | E18: 8021 | F18: 249457 | G18: 3102 | H18: =IF(D17=0,0,D18/D17-1) -> 0.13785453 | I18: =D18/$D$8*100 -> 418.11329
B20: Computed signals
B21: Growth over the series (GHCP ACR) | C21: =D18/D8-1 -> 3.1811329
B22: Average MoM growth, last 4 months | C22: =AVERAGE(H15:H18) -> 0.24161779
B23: Seats added in the series | C23: =C18-C8 -> 2540.2
B24: PRU spend multiplied by | C24: =IF(E8=0,0,E18/E8) -> 572.92857
B27: Paula Silva, Software Global Black Belt | paulasilva@microsoft.com | Microsoft

Sheet Model Mix
B2: DATA
B4: Model Mix, April 2026
B5: Token cost by AI model from db.json (Model Level Details). Shares and concentration are formulas.
B7: Model | C7: Token cost (USD) | D7: Share of bill | E7: Unique users | F7: Input tokens (M) | G7: Output tokens (M) | H7: Cache read tokens (M) | I7: Cache read share | J7: Cache creation tokens (M)
B8: claude opus 4.6 | C8: 100516 | D8: =C8/SUM($C$8:$C$33) -> 0.43381398 | E8: 1450 | F8: 4161 | G8: 503 | H8: 60660 | I8: =IF(F8+G8+H8+J8=0,0,H8/(F8+G8+H8+J8)) -> 0.853801 | J8: 5723
B9: claude sonnet 4.6 | C9: 59960 | D9: =C9/SUM($C$8:$C$33) -> 0.25877956 | E9: 2068 | F9: 4835 | G9: 608 | H9: 55658 | I9: =IF(F9+G9+H9+J9=0,0,H9/(F9+G9+H9+J9)) -> 0.83974049 | J9: 5179
B10: claude opus 4.7 | C10: 19004 | D10: =C10/SUM($C$8:$C$33) -> 0.082018791 | E10: 568 | F10: 155 | G10: 109 | H10: 12144 | I10: =IF(F10+G10+H10+J10=0,0,H10/(F10+G10+H10+J10)) -> 0.87253916 | J10: 1510
B11: claude sonnet 4.5 | C11: 10514 | D11: =C11/SUM($C$8:$C$33) -> 0.045377056 | E11: 1163 | F11: 915 | G11: 88 | H11: 6347 | I11: =IF(F11+G11+H11+J11=0,0,H11/(F11+G11+H11+J11)) -> 0.74129876 | J11: 1212
B12: gpt 5.4 | C12: 9623 | D12: =C12/SUM($C$8:$C$33) -> 0.041531616 | E12: 1408 | F12: 1765 | G12: 140 | H12: 13039 | I12: =IF(F12+G12+H12+J12=0,0,H12/(F12+G12+H12+J12)) -> 0.87252409 | J12: 0
B13: gpt 5.3 codex | C13: 9297 | D13: =C13/SUM($C$8:$C$33) -> 0.040124642 | E13: 1445 | F13: 2531 | G13: 136 | H13: 19820 | I13: =IF(F13+G13+H13+J13=0,0,H13/(F13+G13+H13+J13)) -> 0.88139814 | J13: 0
B14: claude opus 4.6 fast | C14: 5898 | D14: =C14/SUM($C$8:$C$33) -> 0.025455001 | E14: 67 | F14: 9 | G14: 8 | H14: 649 | I14: =IF(F14+G14+H14+J14=0,0,H14/(F14+G14+H14+J14)) -> 0.88419619 | J14: 68
B15: claude opus 4.5 | C15: 4455 | D15: =C15/SUM($C$8:$C$33) -> 0.0192272 | E15: 262 | F15: 240 | G15: 19 | H15: 2116 | I15: =IF(F15+G15+H15+J15=0,0,H15/(F15+G15+H15+J15)) -> 0.798792 | J15: 274
B16: claude haiku 4.5 | C16: 3992 | D16: =C16/SUM($C$8:$C$33) -> 0.017228953 | E16: 1654 | F16: 603 | G16: 189 | H16: 10261 | I16: =IF(F16+G16+H16+J16=0,0,H16/(F16+G16+H16+J16)) -> 0.83674468 | J16: 1210
B17: gpt 4.1 | C17: 2214 | D17: =C17/SUM($C$8:$C$33) -> 0.0095553359 | E17: 1964 | F17: 636 | G17: 20 | H17: 1599 | I17: =IF(F17+G17+H17+J17=0,0,H17/(F17+G17+H17+J17)) -> 0.70909091 | J17: 0
B18: gpt 5.2 | C18: 1412 | D18: =C18/SUM($C$8:$C$33) -> 0.0060940083 | E18: 506 | F18: 297 | G18: 28 | H18: 2827 | I18: =IF(F18+G18+H18+J18=0,0,H18/(F18+G18+H18+J18)) -> 0.89689086 | J18: 0
B19: code review model | C19: 1384 | D19: =C19/SUM($C$8:$C$33) -> 0.0059731639 | E19: 501 | F19: 719 | G19: 665 | H19: 731 | I19: =IF(F19+G19+H19+J19=0,0,H19/(F19+G19+H19+J19)) -> 0.23634012 | J19: 978
... B33: gpt 5.1 codex max | C33: 1 | D33: =C33/SUM($C$8:$C$33) -> 4.3158699e-06 | E33: 3 | F33: 0 | G33: 0 | H33: 0 | I33: =IF(F33+G33+H33+J33=0,0,H33/(F33+G33+H33+J33)) -> 0 | J33: 0
B35: Total | C35: =SUM(C8:C33) -> 231703 | I35: =SUMPRODUCT(H8:H33)/SUMPRODUCT(F8:F33+G8:G33+H8:H33+J8:J33) -> 0.83504412
B36: Claude family share | C36: =SUMIF(B8:B33,"*claude*",C8:C33)/C35 -> 0.88548702
B37: Top 2 models share | C37: =(LARGE(C8:C33,1)+LARGE(C8:C33,2))/C35 -> 0.69259354
B38: Why it matters | C38: Cache reads are 83.5% of all token volume. Stable prefixes and context curation (R4, R5) attack exactly this line.
B40: Paula Silva, Software Global Black Belt | paulasilva@microsoft.com | Microsoft

Sheet Simulator
B2: WHAT-IF
B4: Budget Simulator, R1-R7 Levers
B5: Editable reduction per lever. Combined effect is multiplicative: 1-(1-r1)x...x(1-r7). It can never exceed 100%.
B7: Lever | C7: Reduction (editable) | D7: Attacks | E7: Official band | F7: Note
B8: R1 Output control | C8: 0.06 | D8: output | E8: 40-70% of output | F8: output costs ~4-5x input; instruction blocks cut verbosity
B9: R2 Model routing | C9: 0.1 | D9: whole bill | E9: 40-70% | F9: price per token spans two orders of magnitude; route by task
B10: R3 Local models (BYOK) | C10: 0.02 | D10: routine tasks | E10: single digit to ~15% | F10: BYOK local models do not consume credits; not for completions
B11: R4 Context scoping | C11: 0.08 | D11: input | E11: 40-80% of input | F11: context is often 60%+ of input per turn
B12: R5 Cache and memory | C12: 0.06 | D12: input | E12: 30-50% of input | F12: stable prefixes are not reprocessed; cache reads are cheaper
B13: R6 Repository primitives | C13: 0.03 | D13: input and bill | E13: compound | F13: versioned instructions, agents and prompts
B14: R7 Budgets and measurement | C14: 0 | D14: variance | E14: guardrail | F14: does not cut the run rate; prevents runaway loops
B17: Simulated result
B18: Combined consumption reduction | C18: =1-(1-C8)*(1-C9)*(1-C10)*(1-C11)*(1-C12)*(1-C13)*(1-C14) -> 0.30452127
B19: Mature overage with program (USD/month) | C19: =MAX(0,'Client Intake'!C14*(1-C18)-Engine!C14) -> 33896.204
B20: Mature monthly saving (USD) | C20: =Engine!C16-C19 -> 70558.796
B21: Mature run-rate saving (USD/year) | C21: =C20*12 -> 846705.55
B22: Overage drop at maturity | C22: =IF(Engine!C16=0,0,(Engine!C16-C19)/Engine!C16) -> 0.67549467
B23: FY27 program savings (maturity curve) | C23: ='Forecast FY27'!F22 -> 494617.16
B25: Reference bands: a lean start delivers 20-30% reduction; a mature program 55-70%. Defaults above are lean. Sources sheet holds the references.
B27: Paula Silva, Software Global Black Belt | paulasilva@microsoft.com | Microsoft

Sheet Forecast FY27
B2: BUSINESS CASE
B4: Forecast FY27, The September Curve
B5: Promo covers Jul-Aug. Ramp (yellow) is the program maturation; everything else is formula.
B7: Month | C7: Ramp | D7: No-action overage (USD) | E7: With-program overage (USD) | F7: Monthly saving (USD) | G7: Cumulative saving (USD) | H7: Scenario cost no action (USD) | I7: Scenario cost with program (USD)
B9: FY27 (Microsoft fiscal year)
B10: Jul-26 | C10: 0 | D10: =IF(ROW()-10<'Client Intake'!C16,Engine!$C$17,Engine!$C$16) -> 10254 | E10: =MAX(0,'Client Intake'!$C$14*(1-C10*Simulator!$C$18)-IF(ROW()-10<'Client Intake'!$C$16,Engine!$C$15,Engine!$C$14)) -> 10254 | F10: =D10-E10 -> 0 | G10: =SUM($F$10:F10) -> 0 | H10: =Engine!$C$13+D10 -> 137503 | I10: =Engine!$C$13+E10 -> 137503
B11: Aug-26 | C11: 0.05 | D11: =IF(ROW()-10<'Client Intake'!C16,Engine!$C$17,Engine!$C$16) -> 10254 | E11: =MAX(0,'Client Intake'!$C$14*(1-C11*Simulator!$C$18)-IF(ROW()-10<'Client Intake'!$C$16,Engine!$C$15,Engine!$C$14)) -> 6726.0602 | F11: =D11-E11 -> 3527.9398 | G11: =SUM($F$10:F11) -> 3527.9398 | H11: =Engine!$C$13+D11 -> 137503 | I11: =Engine!$C$13+E11 -> 133975.06
B12: Sep-26 | C12: 0.15 | D12: =IF(ROW()-10<'Client Intake'!C16,Engine!$C$17,Engine!$C$16) -> 104455 | E12: =MAX(0,'Client Intake'!$C$14*(1-C12*Simulator!$C$18)-IF(ROW()-10<'Client Intake'!$C$16,Engine!$C$15,Engine!$C$14)) -> 93871.181 | F12: =D12-E12 -> 10583.819 | G12: =SUM($F$10:F12) -> 14111.759 | H12: =Engine!$C$13+D12 -> 231704 | I12: =Engine!$C$13+E12 -> 221120.18
B13: Oct-26 | C13: 0.3 | D13: =IF(ROW()-10<'Client Intake'!C16,Engine!$C$17,Engine!$C$16) -> 104455 | E13: =MAX(0,'Client Intake'!$C$14*(1-C13*Simulator!$C$18)-IF(ROW()-10<'Client Intake'!$C$16,Engine!$C$15,Engine!$C$14)) -> 83287.361 | F13: =D13-E13 -> 21167.639 | G13: =SUM($F$10:F13) -> 35279.398 | H13: =Engine!$C$13+D13 -> 231704 | I13: =Engine!$C$13+E13 -> 210536.36
B14: Nov-26 | C14: 0.45 | D14: =IF(ROW()-10<'Client Intake'!C16,Engine!$C$17,Engine!$C$16) -> 104455 | E14: =MAX(0,'Client Intake'!$C$14*(1-C14*Simulator!$C$18)-IF(ROW()-10<'Client Intake'!$C$16,Engine!$C$15,Engine!$C$14)) -> 72703.542 | F14: =D14-E14 -> 31751.458 | G14: =SUM($F$10:F14) -> 67030.856 | H14: =Engine!$C$13+D14 -> 231704 | I14: =Engine!$C$13+E14 -> 199952.54
B15: Dec-26 | C15: 0.6 | D15: =IF(ROW()-10<'Client Intake'!C16,Engine!$C$17,Engine!$C$16) -> 104455 | E15: =MAX(0,'Client Intake'!$C$14*(1-C15*Simulator!$C$18)-IF(ROW()-10<'Client Intake'!$C$16,Engine!$C$15,Engine!$C$14)) -> 62119.723 | F15: =D15-E15 -> 42335.277 | G15: =SUM($F$10:F15) -> 109366.13 | H15: =Engine!$C$13+D15 -> 231704 | I15: =Engine!$C$13+E15 -> 189368.72
B16: Jan-27 | C16: 0.75 | D16: =IF(ROW()-10<'Client Intake'!C16,Engine!$C$17,Engine!$C$16) -> 104455 | E16: =MAX(0,'Client Intake'!$C$14*(1-C16*Simulator!$C$18)-IF(ROW()-10<'Client Intake'!$C$16,Engine!$C$15,Engine!$C$14)) -> 51535.903 | F16: =D16-E16 -> 52919.097 | G16: =SUM($F$10:F16) -> 162285.23 | H16: =Engine!$C$13+D16 -> 231704 | I16: =Engine!$C$13+E16 -> 178784.9
B17: Feb-27 | C17: 0.85 | D17: =IF(ROW()-10<'Client Intake'!C16,Engine!$C$17,Engine!$C$16) -> 104455 | E17: =MAX(0,'Client Intake'!$C$14*(1-C17*Simulator!$C$18)-IF(ROW()-10<'Client Intake'!$C$16,Engine!$C$15,Engine!$C$14)) -> 44480.024 | F17: =D17-E17 -> 59974.976 | G17: =SUM($F$10:F17) -> 222260.21 | H17: =Engine!$C$13+D17 -> 231704 | I17: =Engine!$C$13+E17 -> 171729.02
B18: Mar-27 | C18: 0.92 | D18: =IF(ROW()-10<'Client Intake'!C16,Engine!$C$17,Engine!$C$16) -> 104455 | E18: =MAX(0,'Client Intake'!$C$14*(1-C18*Simulator!$C$18)-IF(ROW()-10<'Client Intake'!$C$16,Engine!$C$15,Engine!$C$14)) -> 39540.908 | F18: =D18-E18 -> 64914.092 | G18: =SUM($F$10:F18) -> 287174.3 | H18: =Engine!$C$13+D18 -> 231704 | I18: =Engine!$C$13+E18 -> 166789.91
B19: Apr-27 | C19: 0.96 | D19: =IF(ROW()-10<'Client Intake'!C16,Engine!$C$17,Engine!$C$16) -> 104455 | E19: =MAX(0,'Client Intake'!$C$14*(1-C19*Simulator!$C$18)-IF(ROW()-10<'Client Intake'!$C$16,Engine!$C$15,Engine!$C$14)) -> 36718.556 | F19: =D19-E19 -> 67736.444 | G19: =SUM($F$10:F19) -> 354910.74 | H19: =Engine!$C$13+D19 -> 231704 | I19: =Engine!$C$13+E19 -> 163967.56
B20: May-27 | C20: 0.98 | D20: =IF(ROW()-10<'Client Intake'!C16,Engine!$C$17,Engine!$C$16) -> 104455 | E20: =MAX(0,'Client Intake'!$C$14*(1-C20*Simulator!$C$18)-IF(ROW()-10<'Client Intake'!$C$16,Engine!$C$15,Engine!$C$14)) -> 35307.38 | F20: =D20-E20 -> 69147.62 | G20: =SUM($F$10:F20) -> 424058.36 | H20: =Engine!$C$13+D20 -> 231704 | I20: =Engine!$C$13+E20 -> 162556.38
B21: Jun-27 | C21: 1 | D21: =IF(ROW()-10<'Client Intake'!C16,Engine!$C$17,Engine!$C$16) -> 104455 | E21: =MAX(0,'Client Intake'!$C$14*(1-C21*Simulator!$C$18)-IF(ROW()-10<'Client Intake'!$C$16,Engine!$C$15,Engine!$C$14)) -> 33896.204 | F21: =D21-E21 -> 70558.796 | G21: =SUM($F$10:F21) -> 494617.16 | H21: =Engine!$C$13+D21 -> 231704 | I21: =Engine!$C$13+E21 -> 161145.2
B22: Total FY27 | D22: =SUM(D10:D21) -> 1065058 | E22: =SUM(E10:E21) -> 570440.84 | F22: =SUM(F10:F21) -> 494617.16 | H22: =SUM(H10:H21) -> 2592046 | I22: =SUM(I10:I21) -> 2097428.8
B24: Reading | C24: No-action plateau lands in September. The with-program line bends as R1-R7 mature. Savings accumulate without costing Microsoft a dollar.
B26: Paula Silva, Software Global Black Belt | paulasilva@microsoft.com | Microsoft

Sheet ROI Scenarios
B2: BUSINESS CASE
B4: ROI, The Four FY27 Scenarios
B5: The savings ladder. P3 percentages are editable; everything else recalculates.
B7: P3 discount inputs
B8: P3 published discount | C8: 0.15 | D8: public table, does not beat the ACD
B9: P3 via Deal Desk | C9: 0.2 | D9: subject to eligibility and approval
B11: Scenario | C11: FY27 total cost (USD) | D11: Savings vs A (USD) | E11: What it is
B12: A No discount, no action | C12: ='Forecast FY27'!H22 -> 2592046 | D12: =0 -> 0 | E12: baseline, full overage, no program
B13: B Promo + P3 15% | C13: ='Forecast FY27'!H22-'Forecast FY27'!D22*C8 -> 2432287.3 | D13: =C12-C13 -> 159758.7 | E13: published discount on token overage
B14: C Promo + P3 20% (Deal Desk) | C14: ='Forecast FY27'!H22-'Forecast FY27'!D22*C9 -> 2379034.4 | D14: =C12-C14 -> 213011.6 | E14: beats the ACD; needs approval
B15: D P3 20% + optimization program | C15: ='Forecast FY27'!I22-'Forecast FY27'!E22*C9 -> 1983340.7 | D15: =C12-C15 -> 608705.33 | E15: recommended path: discount on the reduced overage plus R1-R7 savings
B17: Savings decomposition, scenario D
B18: Commercial discount component | C18: ='Forecast FY27'!E22*C9 -> 114088.17 | D18: the P3 cut on the optimized overage
B19: Efficiency redemption component | C19: ='Forecast FY27'!F22 -> 494617.16 | D19: R1-R7 savings; costs Microsoft nothing
B20: Total scenario D savings | C20: =C18+C19 -> 608705.33 | D20: redemption is worth more than the discount
B23: Paula Silva, Software Global Black Belt | paulasilva@microsoft.com | Microsoft

Sheet Action Plan R1-R7
B2: EXECUTION
B4: Action Plan, R1-R7
B5: Owner, due date and status per action. The Dashboard counts these statuses live.
B7: ID | C7: Lever | D7: Action | E7: Owner | F7: Due | G7: Effort | H7: Expected impact | I7: Status | J7: Notes
B8: A01 | C8: R7 Budgets | D8: Enable budgets and alerts per org and cost center (alert 80%, block 100%) | E8: Client platform team | F8: 2026-07-15 | G8: Low | H8: variance guardrail | I8: In progress
B9: A02 | C9: R2 Routing | D9: Publish model allowlist and task-to-model policy (light-first) | E9: GBB + client arch | F9: 2026-07-31 | G9: Medium | H9: frontier share down | I9: Not started
B10: A03 | C10: R1 Output | D10: Roll out instruction blocks limiting output verbosity in top repos | E10: Client dev leads | F10: 2026-08-15 | G10: Low | H10: output tokens down | I10: Not started
B11: A04 | C11: R4 Context | D11: Scope context: #-mentions discipline, trim attachments, kill mega-threads | E11: Client dev leads | F11: 2026-08-15 | G11: Medium | H11: input tokens down | I11: Not started
B12: A05 | C12: R5 Cache | D12: Stabilize system prompts and shared prefixes to raise cache hits | E12: Client platform team | F12: 2026-08-31 | G12: Medium | H12: cache read share up | I12: Not started
B13: A06 | C13: R6 Primitives | D13: Version prompts, instructions and agent definitions in the repo | E13: GBB + client arch | F13: 2026-09-15 | G13: Medium | H13: compound savings | I13: Not started
B14: A07 | C14: R3 BYOK | D14: Pilot local models for routine, non-completion tasks | E14: Client arch | F14: 2026-09-30 | G14: High | H14: routine offload | I14: Not started
B15: A08 | C15: Commercial | D15: Size the P3 and open the Deal Desk case before promo expiry | E15: MSFT account team | F15: 2026-08-15 | G15: Medium | H15: beats the ACD | I15: In progress
B16: A09 | C16: Governance | D16: Stand up the FinOps dashboard and weekly mix review | E16: Client FinOps | F16: 2026-08-01 | G16: Medium | H16: visibility | I16: Not started
B17: A10 | C17: Checkpoint | D17: September review package: real overage vs forecast, milestones | E17: GBB | F17: 2026-09-01 | G17: Low | H17: decision gate | I17: Not started
B19: Paula Silva, Software Global Black Belt | paulasilva@microsoft.com | Microsoft

Sheet 90-Day Plan
B2: EXECUTION
B4: 90-Day Plan, Weekly Cadence
B5: Twelve weeks aligned to the transition. Status dropdowns feed the Dashboard.
B7: Week | C7: Phase | D7: KPI / focus | E7: Main action | F7: Target | G7: Status
B8: W1 | C8: Baseline | D8: Usage projection done | E8: Ingest consumption, read the curve | F8: projection complete | G8: Not started
B9: W2 | C9: Baseline | D9: Model allowlist defined | E9: Publish task-to-model policy | F9: allowlist live | G9: Not started
B10: W3 | C10: Baseline | D10: Team enabled on the change | E10: Enablement session, pick pilot squad | F10: pilot defined | G10: Not started
B11: W4 | C11: Baseline | D11: Per-user budget set | E11: Configure user caps in the pilot | F11: budget live in pilot | G11: Not started
B12: W5 | C12: Instrument | D12: Caching on long prompts | E12: Enable caching, mark system prompts | F12: caching in production | G12: Not started
B13: W6 | C13: Instrument | D13: FinOps dashboard live | E13: Stand up billing overview and alerts | F13: dashboard active | G13: Not started
B14: W7 | C14: Instrument | D14: Model mix under review | E14: Weekly mix review; contain frontier | F14: frontier share falling | G14: Not started
B15: W8 | C15: Instrument | D15: Budgets refined | E15: Recalibrate with 30 days of real data | F15: budgets calibrated | G15: Not started
B16: W9 | C16: Optimize | D16: Primitives published | E16: Standardize prompts in the repo | F16: primitives in use | G16: Not started
B17: W10 | C17: Optimize | D17: Agents scoped and capped | E17: Configure scope, tools and limits | F17: agents governed | G17: Not started
B18: W11 | C18: Optimize | D18: Redemption curve visible | E18: Compare real vs forecast overage | F18: redemption on track | G18: Not started
B19: W12 | C19: Scale | D19: September review ready | E19: Consolidate milestones for checkpoint | F19: review package ready | G19: Not started
B21: Paula Silva, Software Global Black Belt | paulasilva@microsoft.com | Microsoft

Sheet Monthly Checkpoints
B2: EXECUTION
B4: Monthly Checkpoints
B5: Six months. September is the lock: promo expires, real overage shows up.
B7: Month | C7: Checkpoint | D7: Primary indicator | E7: Target | F7: Status
B8: Jul-26 | C8: Promo active, baseline measured | D8: overage covered by promo | E8: clear baseline | F8: Not started
B9: Aug-26 | C9: Instrumentation live | D9: caching and dashboard active | E9: foundation ready | F9: Not started
B10: Sep-26 | C10: REVIEW, promo expires | D10: real overage appears; milestones met? | E10: extension decided | F10: Not started
B11: Oct-26 | C11: Redemption maturing | D11: overage falling vs plateau | E11: descending trajectory | F11: Not started
B12: Nov-26 | C12: Continuous optimization | D12: model mix under control | E12: frontier share lower | F12: Not started
B13: Dec-26 | C13: Halfway point | D13: redemption ~60% mature | E13: savings accumulating | F13: Not started
B15: Paula Silva, Software Global Black Belt | paulasilva@microsoft.com | Microsoft

Sheet KPI Tracker
B2: EXECUTION
B4: KPI Tracker, Enter Actuals Weekly
B5: Yellow cells take real data. Variance and traffic lights are automatic.
B7: KPI | C7: Unit | D7: Target | E7: W1 | F7: W2 | G7: W3 | H7: W4 | I7: W5 | J7: W6 | K7: W7 | L7: W8 | M7: Latest | N7: Variance vs target
B8: Monthly overage run-rate | C8: USD/month | D8: =Simulator!C19 -> 33896.204 | M8: =IFERROR(LOOKUP(2,1/(E8:L8<>""),E8:L8),"") | N8: =IF(M8="","",M8-D8)
B9: Frontier model share of bill | C9: % | D9: 0.1 | M9: =IFERROR(LOOKUP(2,1/(E9:L9<>""),E9:L9),"") | N9: =IF(M9="","",M9-D9)
B10: Cache read share of tokens | C10: % | D10: 0.85 | M10: =IFERROR(LOOKUP(2,1/(E10:L10<>""),E10:L10),"") | N10: =IF(M10="","",M10-D10)
B11: Seats over per-user budget | C11: count | D11: 0 | M11: =IFERROR(LOOKUP(2,1/(E11:L11<>""),E11:L11),"") | N11: =IF(M11="","",M11-D11)
B12: Weekly active users (WAU) | C12: % | D12: 0.65 | M12: =IFERROR(LOOKUP(2,1/(E12:L12<>""),E12:L12),"") | N12: =IF(M12="","",M12-D12)
B13: Actions done (Action Plan) | C13: count | D13: =COUNTIF('Action Plan R1-R7'!I8:I17,"Done") -> 0 | M13: =IFERROR(LOOKUP(2,1/(E13:L13<>""),E13:L13),"") | N13: =IF(M13="","",M13-D13)
B15: Note: for the overage and frontier KPIs, below target is good. Read the variance sign accordingly.
B17: Paula Silva, Software Global Black Belt | paulasilva@microsoft.com | Microsoft

Sheet Governance
B2: GOVERNANCE
B4: Budgets and Guardrails
B5: Caps computed from the engine. Rule of thumb: alert at 80%, block at 100%.
B8: Mature target overage (USD/month) | C8: =Simulator!C19 -> 33896.204
B9: Licensed seats | C9: ='Client Intake'!C11+'Client Intake'!C12 -> 4131
B10: Cap per user (USD/month) | C10: =IF(C9=0,0,C8/C9) -> 8.2053266
B11: Cost centers | C11: ='Client Intake'!C20 -> 10
B12: Cap per cost center (USD/month) | C12: =IF(C11=0,0,C8/C11) -> 3389.6204
B13: Alert margin | C13: 0.8
B14: Per-user alert trigger (USD) | C14: =C10*C13 -> 6.5642613
B15: Per-cost-center alert trigger (USD) | C15: =C12*C13 -> 2711.6963
B17: Three-layer metrics model
B18: Layer | C18: The question it answers | D18: Primary owner
B19: 1 Cost and governance | C19: Is the financial impact under control? Overage trajectory, mix, budgets | D19: GBB + client data
B20: 2 Platform and architecture | C20: Is the foundation being built? Primitives, caching, agents governed | D20: Partners + GBB
B21: 3 Organizational outcome | C21: Did real value show up? Faster, safer delivery at the org level | D21: All three sides
B23: Trap to avoid: the AI productivity paradox. Individual output rises while org throughput stalls. Measure layer 3, not anecdotes.
B25: Paula Silva, Software Global Black Belt | paulasilva@microsoft.com | Microsoft

Sheet Maturity
B2: DIAGNOSTIC
B4: Maturity Assessment
B5: Score each dimension 1-5. Stage and color are automatic.
B7: Dimension | C7: Score (1-5) | D7: What to assess
B8: Model policy and routing | C8: 3 | D8: governance over which model per task
B9: Context curation and cache | C9: 3 | D9: lean context discipline and caching
B10: Repository primitives | C10: 3 | D10: standardized, versioned prompts and instructions
B11: Agent architecture | C11: 2 | D11: agents with scope, tools and caps
B12: FinOps and observability | C12: 2 | D12: cost dashboards, alerts and budgets live
B14: Total score | C14: =SUM(C8:C12) -> 13
B15: Stage | C15: =IF(C14<=10,"Initial",IF(C14<=18,"Evolving","Mature")) -> Evolving
B18: Paula Silva, Software Global Black Belt | paulasilva@microsoft.com | Microsoft

Sheet Glossary
B2: REFERENCE
B4: Glossary
B5: The terms that show up in the conversation, in plain language.
B7: Term | C7: Definition
B8: UBB | C8: Usage-Based Billing: AI consumption above the included pool is metered and billed
B9: Credit | C9: the billing unit; 1 credit = USD 0.01 at list
B10: Included pool | C10: credits bundled per seat, pooled at the org level (Business 1,900; Enterprise 3,900 per seat per month)
B11: Promo pool | C11: the 90-day promotion: Business 3,000 and Enterprise 7,000 credits per seat, Jun-Aug 2026
B12: Overage | C12: consumption above the pool, billed at price per credit
B13: Pooling | C13: heavy and light users share the same org pool; no credits expire individually
B14: PRU | C14: Premium Request Units, the old metering model with an opaque cap
B15: P3 | C15: Pre-Purchase Plan: committed credit purchase with discount band
B16: ACD | C16: Azure Commitment Discount: the discount level a P3 must beat to be worth it
B17: Deal Desk | C17: the approval path for above-published P3 discounts
B18: R1-R7 | C18: the seven technical optimization levers detailed in the runbook and in this kit
... B21: Frontier model | C21: top-end model class; the most expensive tokens on the bill
B23: Paula Silva, Software Global Black Belt | paulasilva@microsoft.com | Microsoft

Sheet Sources
B2: REFERENCE
B4: Sources and Assumptions
B5: Where every number comes from, and what is editable.
B7: Item | C7: Origin / note
B8: BTG billing data | C8: GitHub Token Based Billing report, fiscal month April 2026 (official). Consumption USD 231,704; promo scenario USD 137,624.
B9: db.json v2.0.0 | C9: Brazil UBB consolidated collection. BTG row: today 130,948; no action 231,704; promo 137,624; licenses 127,249. This kit is coherent with it.
B10: Engine reconciliation | C10: The engine computes the promo scenario at ~USD 137.5k from CB 1,693 / CE 2,438. The official report shows 137,624; the USD ~121 gap comes from seat split rounding in the source. Both round to +5% vs today.
B11: Monthly FY26 series | C11: db.json uso_mensal, MSX FY26 (Jul/25 to May/26). GHCP ACR grew 4.2x over the series.
B12: Model mix | C12: db.json modelos_tokens, Model Level Details April 2026. Sum matches the 231,704 consumption.
B13: Plan table | C13: GitHub Copilot list: Business USD 19 and 1,900 credits; Enterprise USD 39 and 3,900; promo 3,000 and 7,000. Verify at docs.github.com before client use.
B14: R1-R7 bands | C14: Official mechanics documented in the PT-BR runbook v2.1.0 and the internal HTML v8. Bands are ranges with sources, never promises.
B15: Simulator defaults | C15: Lean-start values; combined effect is multiplicative. Mature programs reach 55-70%.
B16: P3 and Deal Desk | C16: Subject to eligibility and approval. Not a GitHub announcement; do not present as guaranteed.
B17: Promo window | C17: 90 days, June to August 2026, expiry 2026-09-01. The September jump is the decision deadline.
B18: FY27 ramp curve | C18: Editable assumption reflecting typical program maturation; replace with actuals as they land.
B20: Paula Silva, Software Global Black Belt | paulasilva@microsoft.com | Microsoft
